tcfg/__init__.py
tcfg/config.py
tcfg/type_check/__init__.py
tcfg/type_check/base.py
tcfg/type_check/custom_types.py
tcfg/type_check/exceptions.py
tcfg-0.4.6.dist-info/METADATA
tcfg-0.4.6.dist-info/WHEEL
tcfg-0.4.6.dist-info/licenses/LICENSE
tcfg-0.4.6.dist-info/RECORD
