Metadata-Version: 2.1
Name: tcfg
Version: 0.4.6
Summary: Typed dataclass like configuration objects
Project-URL: Homepage, https://github.com/Tired-Fox/tcfg
Project-URL: Documentation, https://tired-fox.github.io/tcfg
Author-email: Tired Fox <zboehm104@gmail.com>
License-Expression: MIT
License-File: LICENSE
Classifier: License :: OSI Approved :: MIT License
Classifier: Operating System :: OS Independent
Classifier: Programming Language :: Python :: 3
Requires-Python: >=3.9
Requires-Dist: pyyaml>=6
Requires-Dist: saimll
Requires-Dist: toml>=0.10.2
Provides-Extra: all
Requires-Dist: pyyaml; extra == 'all'
Requires-Dist: toml; extra == 'all'
Provides-Extra: toml
Requires-Dist: toml; extra == 'toml'
Provides-Extra: yaml
Requires-Dist: pyyaml; extra == 'yaml'
